CHANGELOG.md
tursu-1.0.0.dist-info/METADATA
tursu-1.0.0.dist-info/WHEEL
tursu-1.0.0.dist-info/entry_points.txt
tursu-1.0.0.dist-info/licenses/LICENSE
tursu/__init__.py
tursu/domain/__init__.py
tursu/domain/model/__init__.py
tursu/domain/model/gherkin.py
tursu/domain/model/steps.py
tursu/domain/model/testmod.py
tursu/entrypoints/__init__.py
tursu/entrypoints/cli.py
tursu/entrypoints/plugin.py
tursu/py.typed
tursu/runtime/__init__.py
tursu/runtime/exceptions.py
tursu/runtime/pattern_matcher.py
tursu/runtime/registry.py
tursu/runtime/runner.py
tursu/service/__init__.py
tursu/service/ast/__init__.py
tursu/service/ast/astfunction.py
tursu/service/ast/astmodule.py
tursu/service/compiler.py
tursu/shared/__init__.py
tursu/shared/utils.py
tursu-1.0.0.dist-info/RECORD
