Metadata-Version: 2.1
Name: tursu
Version: 1.0.0
Summary: 🎬 A pytest plugin that transpiles Gherkin feature files to Python using AST, enforcing typing for ease of use and debugging.
Author-Email: Guillaume Gauvrit <guillaume@gauvr.it>
License: MIT
Classifier: Development Status :: 5 - Production/Stable
Classifier: Intended Audience :: Developers
Classifier: Framework :: Pytest
Classifier: License :: OSI Approved :: MIT License
Classifier: Topic :: Utilities
Classifier: Topic :: Software Development :: Testing
Classifier: Topic :: Software Development :: Libraries :: Python Modules
Classifier: Programming Language :: Python :: 3
Classifier: Programming Language :: Python :: 3.10
Classifier: Programming Language :: Python :: 3.11
Classifier: Programming Language :: Python :: 3.12
Classifier: Programming Language :: Python :: 3.13
Classifier: Typing :: Typed
Project-URL: Homepage, https://mardiros.github.io/tursu
Project-URL: Documentation, https://mardiros.github.io/tursu
Project-URL: Repository, https://github.com/mardiros/tursu.git
Project-URL: Issues, https://github.com/mardiros/tursu/issues
Project-URL: Changelog, https://mardiros.github.io/tursu/user/changelog.html
Requires-Python: >=3.10
Requires-Dist: gherkin-official>=32.0.0
Requires-Dist: pydantic>=2.10.6
Requires-Dist: pytest>=8.3.5
Requires-Dist: venusian<4,>=3.1.1
Provides-Extra: docs
Requires-Dist: furo>=2024.5.6; extra == "docs"
Requires-Dist: linkify-it-py<3,>=2.0.3; extra == "docs"
Requires-Dist: myst-parser<4,>=3.0.0; python_version < "3.10" and extra == "docs"
Requires-Dist: myst-parser<5,>=4.0.0; python_version >= "3.10" and extra == "docs"
Requires-Dist: sphinx<8,>=7.0.1; extra == "docs"
Requires-Dist: sphinx-autodoc2<1,>=0.5.0; extra == "docs"
